milestone_timer/__init__.py
milestone_timer/timer.py
milestone_timer-1.0.0.dist-info/LICENSE
milestone_timer-1.0.0.dist-info/METADATA
milestone_timer-1.0.0.dist-info/WHEEL
milestone_timer-1.0.0.dist-info/RECORD
